Metadata-Version: 2.1
Name: odoo8-addon-sale-exceptions
Version: 8.0.1.0.0.99.dev34
Summary: Custom exceptions on sale order
Home-page: http://www.akretion.com
Author: Akretion,Odoo Community Association (OCA)
Author-email: support@odoo-community.org
License: UNKNOWN
Platform: UNKNOWN
Classifier: Programming Language :: Python
Classifier: Framework :: Odoo
Classifier: Framework :: Odoo :: 8.0
Requires-Python: ~=2.7
Requires-Dist: odoo (<9.0a,>=8.0a)
